pollychem/__init__.py
pollychem/dataset_loader.py
pollychem/featurize.py
pollychem/maplight.py
pollychem/model.py
pollychem/preprocess.py
pollychem/utils.py
pollychem-0.1.dist-info/METADATA
pollychem-0.1.dist-info/WHEEL
pollychem-0.1.dist-info/top_level.txt
pollychem-0.1.dist-info/RECORD
