Metadata-Version: 2.1
Name: pollychem
Version: 0.1
Author: Elucidata
Author-email: rohit.swami@elucidata.io
Requires-Dist: Cython ==3.0.10
Requires-Dist: chembl-webresource-client ==0.10.9
Requires-Dist: cryptography ==42.0.5
Requires-Dist: datamol ==0.12.4
Requires-Dist: dgl ==2.1.0
Requires-Dist: dgllife ==0.3.2
Requires-Dist: huggingface-hub ==0.22.2
Requires-Dist: joblib ==1.3.2
Requires-Dist: keras ==3.0.5
Requires-Dist: matplotlib ==3.8.3
Requires-Dist: medchem ==2.0.4
Requires-Dist: mlflow ==2.11.1
Requires-Dist: molfeat ==0.10.0
Requires-Dist: numpy ==1.26.4
Requires-Dist: pandas ==2.2.1
Requires-Dist: pubchempy ==1.0.4
Requires-Dist: pytdc ==0.3.6
Requires-Dist: rdkit ==2023.9.5
Requires-Dist: scikit-learn ==1.4.1.post1
Requires-Dist: scikit-optimize ==0.10.1
Requires-Dist: scipy ==1.12.0
Requires-Dist: seaborn ==0.13.2
Requires-Dist: tensorflow ==2.16.1
Requires-Dist: torch ==2.2.1
Requires-Dist: transformers ==4.39.3
Requires-Dist: urllib3 ==2.0.7
Requires-Dist: xgboost ==2.0.3
Requires-Dist: splito ==0.1.2
